Workbook
Name Slicer_Category: #N/A
Name Slicer_Region: #N/A

Sheet Dashboard
B2: RetailPulse Inc. — Regional Profitability Dashboard
B3: ="Data as of: "&TEXT(TODAY(),"mmmm dd, yyyy")&" | 6,500 transactions, FY2024-2025" -> Data as of: September 30, 2026 | 6,500 transactions, FY2024-2025
B8: Total Revenue | E8: Net Margin% | H8: Loss-Making Transactions | K8: Avg Discount Rate
B9: =SUM('Cleaned Data'!M2:M6501) -> 1653907.6 | E9: =AVERAGE('Cleaned Data'!O2:O6501) -> 0.38775664 | H9: =COUNTIF('Cleaned Data'!O2:O6501,"<0")/COUNTA('Cleaned Data'!A2:A6501) -> 0.017692308 | K9: =AVERAGE('Cleaned Data'!J2:J6501) -> 0.112392

Sheet Read Me
A1: RetailPulse Inc. — Raw Sales Transactions
A3: Source: Simulated POS export, FY2024-FY2025
A4: Rows: 6,598
A6: Purpose:
A7: This is a raw, unprocessed export as it would arrive from a POS/transactions system.
A8: It intentionally contains realistic data quality issues you would encounter on the job:
A10: Known issues to expect (do not fix here — clean on a copy):
A11: - Inconsistent text casing/spacing in Region and Category (e.g. 'north', 'NORTH ', 'North')
A12: - Inconsistent Date formats (ISO, US, day-first, and long-form text dates)
A13: - Missing values scattered in Date, Store, CustomerSegment, UnitPrice, DiscountPct, UnitCost, Returned
A14: - Inconsistent values in Returned (Yes/No, Y/N, 1/0, blank)
A15: - Duplicate transaction rows
... A20: Column Dictionary:
A21: TransactionID | B21: Unique identifier for each sales transaction
A22: Date | B22: Date of transaction (formats are inconsistent — needs standardizing)
A23: Region | B23: Sales region: North / South / East / West (casing inconsistent)
A24: Store | B24: Store code within region, e.g. N-003
A25: Category | B25: Product category (casing inconsistent)
A26: Product | B26: Product name
A27: CustomerSegment | B27: Member vs Non-Member (loyalty program status)
A28: UnitsSold | B28: Number of units sold in the transaction
A29: UnitPrice | B29: Selling price per unit, USD
A30: DiscountPct | B30: Discount applied, as a decimal fraction (0.10 = 10%)
A31: UnitCost | B31: Cost per unit to the business, USD
A32: Returned | B32: Whether the transaction was later returned (format inconsistent)

Sheet Cleaned Data
A1: TransactionID | B1: Date | C1: Region | D1: Store | E1: Category | F1: Product | G1: CustomerSegment | H1: UnitSold | I1: UnitPrice | J1: DiscountPct | K1: UnitCost | L1: Returned | M1: Revenue | N1: GrossProfit | O1: NetMarginPct | P1: Month | Q1: Quarter
A2: TXN-100001 | B2: 45832 | C2: North | D2: N-001 | E2: Grocery | F2: Snack Box | G2: Non-Member | H2: 2 | I2: 7.91 | J2: 0.068 | K2: 5.22 | L2: No | M2: =ROUND(H2*I2*(1-J2),2) -> 14.74 | N2: =ROUND(M2-(H2*K2),2) -> 4.3 | O2: =IFERROR(N2/M2,0) -> 0.2917232 | P2: =IF(B2="","",TEXT(B2,"mmm-yyyy")) -> Jun-2025 | Q2: =IF(B2="","","Q"&ROUNDUP(MONTH(B2)/3,0)&"-"&YEAR(B2)) -> Q2-2025
A3: TXN-100002 | B3: 45807 | C3: North | D3: N-010 | E3: Apparel | F3: Men's T-Shirt | G3: Non-Member | H3: 2 | I3: 24.84 | J3: 0 | K3: 10.8 | L3: No | M3: =ROUND(H3*I3*(1-J3),2) -> 49.68 | N3: =ROUND(M3-(H3*K3),2) -> 28.08 | O3: =IFERROR(N3/M3,0) -> 0.56521739 | P3: =IF(B3="","",TEXT(B3,"mmm-yyyy")) -> May-2025 | Q3: =IF(B3="","","Q"&ROUNDUP(MONTH(B3)/3,0)&"-"&YEAR(B3)) -> Q2-2025
A4: TXN-100003 | B4: 46007 | C4: South | D4: S-012 | E4: Grocery | F4: Sparkling Water 12pk | G4: Non-Member | H4: 1 | I4: 12.88 | J4: 0.245 | K4: 7.62 | L4: No | M4: =ROUND(H4*I4*(1-J4),2) -> 9.72 | N4: =ROUND(M4-(H4*K4),2) -> 2.1 | O4: =IFERROR(N4/M4,0) -> 0.21604938 | P4: =IF(B4="","",TEXT(B4,"mmm-yyyy")) -> Dec-2025 | Q4: =IF(B4="","","Q"&ROUNDUP(MONTH(B4)/3,0)&"-"&YEAR(B4)) -> Q4-2025
A5: TXN-100004 | B5: 45913 | C5: South | D5: S-012 | E5: Apparel | F5: Winter Jacket | G5: Member | H5: 2 | I5: 31.33 | J5: 0.229 | K5: 17.03 | L5: No | M5: =ROUND(H5*I5*(1-J5),2) -> 48.31 | N5: =ROUND(M5-(H5*K5),2) -> 14.25 | O5: =IFERROR(N5/M5,0) -> 0.29496999 | P5: =IF(B5="","",TEXT(B5,"mmm-yyyy")) -> Sep-2025 | Q5: =IF(B5="","","Q"&ROUNDUP(MONTH(B5)/3,0)&"-"&YEAR(B5)) -> Q3-2025
A6: TXN-100005 | B6: 45720 | C6: North | D6: N-007 | E6: Electronics | F6: Smart Watch | G6: Unknown | H6: 3 | I6: 191.02 | J6: 0.027 | K6: 147.29 | L6: No | M6: =ROUND(H6*I6*(1-J6),2) -> 557.59 | N6: =ROUND(M6-(H6*K6),2) -> 115.72 | O6: =IFERROR(N6/M6,0) -> 0.207536 | P6: =IF(B6="","",TEXT(B6,"mmm-yyyy")) -> Mar-2025 | Q6: =IF(B6="","","Q"&ROUNDUP(MONTH(B6)/3,0)&"-"&YEAR(B6)) -> Q1-2025
A7: TXN-100006 | B7: 45977 | C7: North | D7: N-015 | E7: Apparel | F7: Casual Dress | G7: Member | H7: 1 | I7: 81.01 | J7: 0.09 | K7: 43.16 | L7: No | M7: =ROUND(H7*I7*(1-J7),2) -> 73.72 | N7: =ROUND(M7-(H7*K7),2) -> 30.56 | O7: =IFERROR(N7/M7,0) -> 0.41454151 | P7: =IF(B7="","",TEXT(B7,"mmm-yyyy")) -> Nov-2025 | Q7: =IF(B7="","","Q"&ROUNDUP(MONTH(B7)/3,0)&"-"&YEAR(B7)) -> Q4-2025
A8: TXN-100007 | B8: 45810 | C8: South | D8: S-012 | E8: Electronics | F8: Wireless Earbuds | G8: Non-Member | H8: 3 | I8: 237.59 | J8: 0 | K8: 189.55 | L8: No | M8: =ROUND(H8*I8*(1-J8),2) -> 712.77 | N8: =ROUND(M8-(H8*K8),2) -> 144.12 | O8: =IFERROR(N8/M8,0) -> 0.20219706 | P8: =IF(B8="","",TEXT(B8,"mmm-yyyy")) -> Jun-2025 | Q8: =IF(B8="","","Q"&ROUNDUP(MONTH(B8)/3,0)&"-"&YEAR(B8)) -> Q2-2025
A9: TXN-100008 | B9: 45525 | C9: North | D9: N-007 | E9: Apparel | F9: Winter Jacket | G9: Non-Member | H9: 4 | I9: 32.08 | J9: 0.061 | K9: 14.54 | L9: No | M9: =ROUND(H9*I9*(1-J9),2) -> 120.49 | N9: =ROUND(M9-(H9*K9),2) -> 62.33 | O9: =IFERROR(N9/M9,0) -> 0.51730434 | P9: =IF(B9="","",TEXT(B9,"mmm-yyyy")) -> Aug-2024 | Q9: =IF(B9="","","Q"&ROUNDUP(MONTH(B9)/3,0)&"-"&YEAR(B9)) -> Q3-2024
A10: TXN-100009 | B10: 45551 | C10: North | D10: N-010 | E10: Grocery | F10: Sparkling Water 12pk | G10: Member | H10: 6 | I10: 19.04 | J10: 0.127 | K10: 10.94 | L10: No | M10: =ROUND(H10*I10*(1-J10),2) -> 99.73 | N10: =ROUND(M10-(H10*K10),2) -> 34.09 | O10: =IFERROR(N10/M10,0) -> 0.34182292 | P10: =IF(B10="","",TEXT(B10,"mmm-yyyy")) -> Sep-2024 | Q10: =IF(B10="","","Q"&ROUNDUP(MONTH(B10)/3,0)&"-"&YEAR(B10)) -> Q3-2024
A11: TXN-100010 | B11: 45683 | C11: South | D11: S-011 | E11: Apparel | F11: Men's T-Shirt | G11: Member | H11: 2 | I11: 39.05 | J11: 0.205 | K11: 15.81 | L11: No | M11: =ROUND(H11*I11*(1-J11),2) -> 62.09 | N11: =ROUND(M11-(H11*K11),2) -> 30.47 | O11: =IFERROR(N11/M11,0) -> 0.49073925 | P11: =IF(B11="","",TEXT(B11,"mmm-yyyy")) -> Jan-2025 | Q11: =IF(B11="","","Q"&ROUNDUP(MONTH(B11)/3,0)&"-"&YEAR(B11)) -> Q1-2025
A12: TXN-100011 | B12: 45653 | C12: East | D12: E-002 | E12: Electronics | F12: Power Bank | G12: Member | H12: 6 | I12: 111.54 | J12: 0.048 | K12: 83.47 | L12: Unknown | M12: =ROUND(H12*I12*(1-J12),2) -> 637.12 | N12: =ROUND(M12-(H12*K12),2) -> 136.3 | O12: =IFERROR(N12/M12,0) -> 0.21393144 | P12: =IF(B12="","",TEXT(B12,"mmm-yyyy")) -> Dec-2024 | Q12: =IF(B12="","","Q"&ROUNDUP(MONTH(B12)/3,0)&"-"&YEAR(B12)) -> Q4-2024
A13: TXN-100012 | B13: 45524 | C13: West | D13: W-003 | E13: Apparel | F13: Women's Jeans | G13: Non-Member | H13: 3 | I13: 93.22 | J13: 0.065 | K13: 44.82 | L13: No | M13: =ROUND(H13*I13*(1-J13),2) -> 261.48 | N13: =ROUND(M13-(H13*K13),2) -> 127.02 | O13: =IFERROR(N13/M13,0) -> 0.48577329 | P13: =IF(B13="","",TEXT(B13,"mmm-yyyy")) -> Aug-2024 | Q13: =IF(B13="","","Q"&ROUNDUP(MONTH(B13)/3,0)&"-"&YEAR(B13)) -> Q3-2024
... A79: TXN-100078 | B79: 45646 | C79: East | D79: E-004 | E79: Home Goods | F79: LED Desk Lamp | G79: Non-Member | H79: 8 | I79: 40.33 | J79: 0.051 | K79: 18.66 | L79: No | M79: =ROUND(H79*I79*(1-J79),2) -> 306.19 | N79: =ROUND(M79-(H79*K79),2) -> 156.91 | O79: =IFERROR(N79/M79,0) -> 0.51245958 | P79: =IF(B79="","",TEXT(B79,"mmm-yyyy")) -> Dec-2024 | Q79: =IF(B79="","","Q"&ROUNDUP(MONTH(B79)/3,0)&"-"&YEAR(B79)) -> Q4-2024
A80: TXN-100079 | C80: East | D80: E-014 | E80: Electronics | F80: Bluetooth Speaker | G80: Member | H80: 7 | I80: 39.32 | J80: 0.07 | K80: 28.93 | L80: No | M80: =ROUND(H80*I80*(1-J80),2) -> 255.97 | N80: =ROUND(M80-(H80*K80),2) -> 53.46 | O80: =IFERROR(N80/M80,0) -> 0.2088526
A81: TXN-100080 | B81: 45889 | C81: North | D81: N-013 | E81: Beauty | F81: Face Moisturizer | G81: Member | H81: 3 | I81: 47.22 | J81: 0.072 | K81: 20.89 | L81: No | M81: =ROUND(H81*I81*(1-J81),2) -> 131.46 | N81: =ROUND(M81-(H81*K81),2) -> 68.79 | O81: =IFERROR(N81/M81,0) -> 0.52327704 | P81: =IF(B81="","",TEXT(B81,"mmm-yyyy")) -> Aug-2025 | Q81: =IF(B81="","","Q"&ROUNDUP(MONTH(B81)/3,0)&"-"&YEAR(B81)) -> Q3-2025
A82: TXN-100081 | B82: 45859 | C82: North | D82: N-010 | E82: Electronics | F82: Wireless Earbuds | G82: Non-Member | H82: 4 | I82: 155.23 | J82: 0.059 | K82: 103.56 | L82: No | M82: =ROUND(H82*I82*(1-J82),2) -> 584.29 | N82: =ROUND(M82-(H82*K82),2) -> 170.05 | O82: =IFERROR(N82/M82,0) -> 0.29103699 | P82: =IF(B82="","",TEXT(B82,"mmm-yyyy")) -> Jul-2025 | Q82: =IF(B82="","","Q"&ROUNDUP(MONTH(B82)/3,0)&"-"&YEAR(B82)) -> Q3-2025
A83: TXN-100082 | B83: 45889 | C83: West | D83: W-012 | E83: Electronics | F83: Smart Watch | G83: Non-Member | H83: 1 | I83: 71.14 | J83: 0.03 | K83: 52.72 | L83: No | M83: =ROUND(H83*I83*(1-J83),2) -> 69.01 | N83: =ROUND(M83-(H83*K83),2) -> 16.29 | O83: =IFERROR(N83/M83,0) -> 0.23605275 | P83: =IF(B83="","",TEXT(B83,"mmm-yyyy")) -> Aug-2025 | Q83: =IF(B83="","","Q"&ROUNDUP(MONTH(B83)/3,0)&"-"&YEAR(B83)) -> Q3-2025
A84: TXN-100083 | B84: 45519 | C84: North | D84: N-013 | E84: Beauty | F84: Lipstick | G84: Member | H84: 5 | I84: 13.62 | J84: 0 | K84: 4.14 | L84: No | M84: =ROUND(H84*I84*(1-J84),2) -> 68.1 | N84: =ROUND(M84-(H84*K84),2) -> 47.4 | O84: =IFERROR(N84/M84,0) -> 0.69603524 | P84: =IF(B84="","",TEXT(B84,"mmm-yyyy")) -> Aug-2024 | Q84: =IF(B84="","","Q"&ROUNDUP(MONTH(B84)/3,0)&"-"&YEAR(B84)) -> Q3-2024
A85: TXN-100084 | B85: 45388 | C85: West | D85: W-007 | E85: Beauty | F85: Shampoo 300ml | G85: Non-Member | H85: 5 | I85: 11.95 | J85: 0.194 | K85: 4.82 | L85: No | M85: =ROUND(H85*I85*(1-J85),2) -> 48.16 | N85: =ROUND(M85-(H85*K85),2) -> 24.06 | O85: =IFERROR(N85/M85,0) -> 0.49958472 | P85: =IF(B85="","",TEXT(B85,"mmm-yyyy")) -> Apr-2024 | Q85: =IF(B85="","","Q"&ROUNDUP(MONTH(B85)/3,0)&"-"&YEAR(B85)) -> Q2-2024
A86: TXN-100085 | B86: 45851 | C86: North | D86: N-012 | E86: Grocery | F86: Sparkling Water 12pk | G86: Non-Member | H86: 3 | I86: 20.72 | J86: 0.056 | K86: 13.87 | L86: No | M86: =ROUND(H86*I86*(1-J86),2) -> 58.68 | N86: =ROUND(M86-(H86*K86),2) -> 17.07 | O86: =IFERROR(N86/M86,0) -> 0.2908998 | P86: =IF(B86="","",TEXT(B86,"mmm-yyyy")) -> Jul-2025 | Q86: =IF(B86="","","Q"&ROUNDUP(MONTH(B86)/3,0)&"-"&YEAR(B86)) -> Q3-2025
A87: TXN-100086 | B87: 45920 | C87: North | D87: N-006 | E87: Home Goods | F87: LED Desk Lamp | G87: Member | H87: 2 | I87: 15.52 | J87: 0.031 | K87: 6.94 | L87: No | M87: =ROUND(H87*I87*(1-J87),2) -> 30.08 | N87: =ROUND(M87-(H87*K87),2) -> 16.2 | O87: =IFERROR(N87/M87,0) -> 0.53856383 | P87: =IF(B87="","",TEXT(B87,"mmm-yyyy")) -> Sep-2025 | Q87: =IF(B87="","","Q"&ROUNDUP(MONTH(B87)/3,0)&"-"&YEAR(B87)) -> Q3-2025
A88: TXN-100087 | B88: 45949 | C88: West | D88: W-014 | E88: Home Goods | F88: Bath Towel Set | G88: Non-Member | H88: 4 | I88: 86.86 | J88: 0.174 | K88: 38.68 | L88: No | M88: =ROUND(H88*I88*(1-J88),2) -> 286.99 | N88: =ROUND(M88-(H88*K88),2) -> 132.27 | O88: =IFERROR(N88/M88,0) -> 0.46088714 | P88: =IF(B88="","",TEXT(B88,"mmm-yyyy")) -> Oct-2025 | Q88: =IF(B88="","","Q"&ROUNDUP(MONTH(B88)/3,0)&"-"&YEAR(B88)) -> Q4-2025
A89: TXN-100088 | B89: 45345 | C89: South | D89: S-007 | E89: Apparel | F89: Casual Dress | G89: Non-Member | H89: 4 | I89: 116.37 | J89: 0.13 | K89: 51.26 | L89: No | M89: =ROUND(H89*I89*(1-J89),2) -> 404.97 | N89: =ROUND(M89-(H89*K89),2) -> 199.93 | O89: =IFERROR(N89/M89,0) -> 0.49369089 | P89: =IF(B89="","",TEXT(B89,"mmm-yyyy")) -> Feb-2024 | Q89: =IF(B89="","","Q"&ROUNDUP(MONTH(B89)/3,0)&"-"&YEAR(B89)) -> Q1-2024
A90: TXN-100089 | B90: 45651 | C90: West | D90: W-008 | E90: Home Goods | F90: Storage Bin | G90: Member | H90: 1 | I90: 78.14 | J90: 0.104 | K90: 37.09 | L90: No | M90: =ROUND(H90*I90*(1-J90),2) -> 70.01 | N90: =ROUND(M90-(H90*K90),2) -> 32.92 | O90: =IFERROR(N90/M90,0) -> 0.47021854 | P90: =IF(B90="","",TEXT(B90,"mmm-yyyy")) -> Dec-2024 | Q90: =IF(B90="","","Q"&ROUNDUP(MONTH(B90)/3,0)&"-"&YEAR(B90)) -> Q4-2024
A91: TXN-100090 | B91: 45945 | C91: West | D91: W-004 | E91: Grocery | F91: Sparkling Water 12pk | G91: Member | H91: 1 | I91: 14 | J91: 0.074 | K91: 9.97 | L91: No | M91: =ROUND(H91*I91*(1-J91),2) -> 12.96 | N91: =ROUND(M91-(H91*K91),2) -> 2.99 | O91: =IFERROR(N91/M91,0) -> 0.23070988 | P91: =IF(B91="","",TEXT(B91,"mmm-yyyy")) -> Oct-2025 | Q91: =IF(B91="","","Q"&ROUNDUP(MONTH(B91)/3,0)&"-"&YEAR(B91)) -> Q4-2025
A92: TXN-100091 | B92: 45592 | C92: East | D92: E-003 | E92: Home Goods | F92: LED Desk Lamp | G92: Non-Member | H92: 2 | I92: 73.83 | J92: 0.059 | K92: 29.61 | L92: Yes | M92: =ROUND(H92*I92*(1-J92),2) -> 138.95 | N92: =ROUND(M92-(H92*K92),2) -> 79.73 | O92: =IFERROR(N92/M92,0) -> 0.57380353 | P92: =IF(B92="","",TEXT(B92,"mmm-yyyy")) -> Oct-2024 | Q92: =IF(B92="","","Q"&ROUNDUP(MONTH(B92)/3,0)&"-"&YEAR(B92)) -> Q4-2024
... A136: TXN-100135 | B136: 45841 | C136: South | D136: S-002 | E136: Home Goods | F136: Bath Towel Set | G136: Non-Member | H136: 1 | I136: 59.58 | J136: 0.201 | K136: 23.01 | L136: No | M136: =ROUND(H136*I136*(1-J136),2) -> 47.6 | N136: =ROUND(M136-(H136*K136),2) -> 24.59 | O136: =IFERROR(N136/M136,0) -> 0.51659664 | P136: =IF(B136="","",TEXT(B136,"mmm-yyyy")) -> Jul-2025 | Q136: =IF(B136="","","Q"&ROUNDUP(MONTH(B136)/3,0)&"-"&YEAR(B136)) -> Q3-2025
A137: TXN-100136 | C137: South | D137: S-004 | E137: Apparel | F137: Winter Jacket | G137: Member | H137: 10 | I137: 85.02 | J137: 0.247 | K137: 45.47 | L137: No | M137: =ROUND(H137*I137*(1-J137),2) -> 640.2 | N137: =ROUND(M137-(H137*K137),2) -> 185.5 | O137: =IFERROR(N137/M137,0) -> 0.2897532
A138: TXN-100137 | B138: 45709 | C138: East | D138: E-011 | E138: Home Goods | F138: Throw Pillow | G138: Non-Member | H138: 8 | I138: 45.34 | J138: 0.09 | K138: 18.22 | L138: No | M138: =ROUND(H138*I138*(1-J138),2) -> 330.08 | N138: =ROUND(M138-(H138*K138),2) -> 184.32 | O138: =IFERROR(N138/M138,0) -> 0.55841008 | P138: =IF(B138="","",TEXT(B138,"mmm-yyyy")) -> Feb-2025 | Q138: =IF(B138="","","Q"&ROUNDUP(MONTH(B138)/3,0)&"-"&YEAR(B138)) -> Q1-2025
A139: TXN-100138 | B139: 45921 | C139: West | D139: W-012 | E139: Electronics | F139: Smart Watch | G139: Member | H139: 20 | I139: 79.78 | J139: 0.086 | K139: 56.46 | L139: No | M139: =ROUND(H139*I139*(1-J139),2) -> 1458.38 | N139: =ROUND(M139-(H139*K139),2) -> 329.18 | O139: =IFERROR(N139/M139,0) -> 0.22571621 | P139: =IF(B139="","",TEXT(B139,"mmm-yyyy")) -> Sep-2025 | Q139: =IF(B139="","","Q"&ROUNDUP(MONTH(B139)/3,0)&"-"&YEAR(B139)) -> Q3-2025
A140: TXN-100139 | B140: 45738 | C140: South | D140: S-007 | E140: Home Goods | F140: Storage Bin | G140: Member | H140: 1 | I140: 33.67 | J140: 0.184 | K140: 15.32 | L140: No | M140: =ROUND(H140*I140*(1-J140),2) -> 27.47 | N140: =ROUND(M140-(H140*K140),2) -> 12.15 | O140: =IFERROR(N140/M140,0) -> 0.44230069 | P140: =IF(B140="","",TEXT(B140,"mmm-yyyy")) -> Mar-2025 | Q140: =IF(B140="","","Q"&ROUNDUP(MONTH(B140)/3,0)&"-"&YEAR(B140)) -> Q1-2025
A141: TXN-100140 | B141: 45323 | C141: West | D141: W-005 | E141: Electronics | F141: Bluetooth Speaker | G141: Non-Member | H141: 4 | I141: 275.42 | J141: 0.032 | K141: 209.81 | L141: No | M141: =ROUND(H141*I141*(1-J141),2) -> 1066.43 | N141: =ROUND(M141-(H141*K141),2) -> 227.19 | O141: =IFERROR(N141/M141,0) -> 0.21303789 | P141: =IF(B141="","",TEXT(B141,"mmm-yyyy")) -> Feb-2024 | Q141: =IF(B141="","","Q"&ROUNDUP(MONTH(B141)/3,0)&"-"&YEAR(B141)) -> Q1-2024
A142: TXN-100141 | B142: 45748 | C142: East | D142: E-013 | E142: Grocery | F142: Sparkling Water 12pk | G142: Member | H142: 1 | I142: 20.64 | J142: 0.069 | K142: 12.03 | L142: No | M142: =ROUND(H142*I142*(1-J142),2) -> 19.22 | N142: =ROUND(M142-(H142*K142),2) -> 7.19 | O142: =IFERROR(N142/M142,0) -> 0.37408949 | P142: =IF(B142="","",TEXT(B142,"mmm-yyyy")) -> Apr-2025 | Q142: =IF(B142="","","Q"&ROUNDUP(MONTH(B142)/3,0)&"-"&YEAR(B142)) -> Q2-2025
A143: TXN-100142 | B143: 45800 | C143: East | D143: E-011 | E143: Grocery | F143: Snack Box | G143: Non-Member | H143: 1 | I143: 16.82 | J143: 0.03 | K143: 11.53 | L143: No | M143: =ROUND(H143*I143*(1-J143),2) -> 16.32 | N143: =ROUND(M143-(H143*K143),2) -> 4.79 | O143: =IFERROR(N143/M143,0) -> 0.2935049 | P143: =IF(B143="","",TEXT(B143,"mmm-yyyy")) -> May-2025 | Q143: =IF(B143="","","Q"&ROUNDUP(MONTH(B143)/3,0)&"-"&YEAR(B143)) -> Q2-2025
A144: TXN-100143 | B144: 45820 | C144: East | D144: E-013 | E144: Apparel | F144: Casual Dress | G144: Non-Member | H144: 5 | I144: 53.31 | J144: 0.15 | K144: 22.37 | L144: No | M144: =ROUND(H144*I144*(1-J144),2) -> 226.57 | N144: =ROUND(M144-(H144*K144),2) -> 114.72 | O144: =IFERROR(N144/M144,0) -> 0.50633358 | P144: =IF(B144="","",TEXT(B144,"mmm-yyyy")) -> Jun-2025 | Q144: =IF(B144="","","Q"&ROUNDUP(MONTH(B144)/3,0)&"-"&YEAR(B144)) -> Q2-2025
A145: TXN-100144 | B145: 45843 | C145: East | D145: E-012 | E145: Apparel | F145: Women's Jeans | G145: Non-Member | H145: 1 | I145: 28.88 | J145: 0.125 | K145: 13.89 | L145: No | M145: =ROUND(H145*I145*(1-J145),2) -> 25.27 | N145: =ROUND(M145-(H145*K145),2) -> 11.38 | O145: =IFERROR(N145/M145,0) -> 0.45033637 | P145: =IF(B145="","",TEXT(B145,"mmm-yyyy")) -> Jul-2025 | Q145: =IF(B145="","","Q"&ROUNDUP(MONTH(B145)/3,0)&"-"&YEAR(B145)) -> Q3-2025
A146: TXN-100145 | B146: 45637 | C146: East | D146: E-014 | E146: Electronics | F146: Laptop Stand | G146: Non-Member | H146: 4 | I146: 106.16 | J146: 0 | K146: 82.86 | L146: No | M146: =ROUND(H146*I146*(1-J146),2) -> 424.64 | N146: =ROUND(M146-(H146*K146),2) -> 93.2 | O146: =IFERROR(N146/M146,0) -> 0.21948003 | P146: =IF(B146="","",TEXT(B146,"mmm-yyyy")) -> Dec-2024 | Q146: =IF(B146="","","Q"&ROUNDUP(MONTH(B146)/3,0)&"-"&YEAR(B146)) -> Q4-2024
A147: TXN-100146 | B147: 45882 | C147: West | D147: W-002 | E147: Electronics | F147: Wireless Earbuds | G147: Non-Member | H147: 2 | I147: 261.54 | J147: 0.106 | K147: 198.41 | L147: Unknown | M147: =ROUND(H147*I147*(1-J147),2) -> 467.63 | N147: =ROUND(M147-(H147*K147),2) -> 70.81 | O147: =IFERROR(N147/M147,0) -> 0.15142313 | P147: =IF(B147="","",TEXT(B147,"mmm-yyyy")) -> Aug-2025 | Q147: =IF(B147="","","Q"&ROUNDUP(MONTH(B147)/3,0)&"-"&YEAR(B147)) -> Q3-2025
A148: TXN-100147 | B148: 45445 | C148: East | D148: E-002 | E148: Grocery | F148: Organic Coffee 12oz | G148: Member | H148: 4 | I148: 8.82 | J148: 0.082 | K148: 5.01 | L148: No | M148: =ROUND(H148*I148*(1-J148),2) -> 32.39 | N148: =ROUND(M148-(H148*K148),2) -> 12.35 | O148: =IFERROR(N148/M148,0) -> 0.38129052 | P148: =IF(B148="","",TEXT(B148,"mmm-yyyy")) -> Jun-2024 | Q148: =IF(B148="","","Q"&ROUNDUP(MONTH(B148)/3,0)&"-"&YEAR(B148)) -> Q2-2024
A149: TXN-100148 | B149: 45812 | C149: East | D149: E-010 | E149: Apparel | F149: Winter Jacket | G149: Member | H149: 1 | I149: 26.38 | J149: 0.056 | K149: 11.48 | L149: No | M149: =ROUND(H149*I149*(1-J149),2) -> 24.9 | N149: =ROUND(M149-(H149*K149),2) -> 13.42 | O149: =IFERROR(N149/M149,0) -> 0.53895582 | P149: =IF(B149="","",TEXT(B149,"mmm-yyyy")) -> Jun-2025 | Q149: =IF(B149="","","Q"&ROUNDUP(MONTH(B149)/3,0)&"-"&YEAR(B149)) -> Q2-2025
... A251: TXN-100250 | B251: 45614 | C251: West | D251: W-002 | E251: Grocery | F251: Snack Box | G251: Non-Member | H251: 1 | I251: 13.65 | J251: 0.01 | K251: 7.93 | L251: No | M251: =ROUND(H251*I251*(1-J251),2) -> 13.51 | N251: =ROUND(M251-(H251*K251),2) -> 5.58 | O251: =IFERROR(N251/M251,0) -> 0.41302739 | P251: =IF(B251="","",TEXT(B251,"mmm-yyyy")) -> Nov-2024 | Q251: =IF(B251="","","Q"&ROUNDUP(MONTH(B251)/3,0)&"-"&YEAR(B251)) -> Q4-2024
A252: TXN-100251 | C252: East | D252: E-014 | E252: Grocery | F252: Olive Oil 500ml | G252: Member | H252: 1 | I252: 24.46 | J252: 0.065 | K252: 13.93 | L252: No | M252: =ROUND(H252*I252*(1-J252),2) -> 22.87 | N252: =ROUND(M252-(H252*K252),2) -> 8.94 | O252: =IFERROR(N252/M252,0) -> 0.39090512
A253: TXN-100252 | B253: 45617 | C253: North | D253: N-006 | E253: Apparel | F253: Men's T-Shirt | G253: Member | H253: 3 | I253: 41.03 | J253: 0.042 | K253: 17.01 | L253: No | M253: =ROUND(H253*I253*(1-J253),2) -> 117.92 | N253: =ROUND(M253-(H253*K253),2) -> 66.89 | O253: =IFERROR(N253/M253,0) -> 0.56724898 | P253: =IF(B253="","",TEXT(B253,"mmm-yyyy")) -> Nov-2024 | Q253: =IF(B253="","","Q"&ROUNDUP(MONTH(B253)/3,0)&"-"&YEAR(B253)) -> Q4-2024
A254: TXN-100253 | B254: 45860 | C254: West | D254: W-014 | E254: Home Goods | F254: Ceramic Mug Set | G254: Non-Member | H254: 1 | I254: 87.01 | J254: 0.004 | K254: 21.19 | L254: No | M254: =ROUND(H254*I254*(1-J254),2) -> 86.66 | N254: =ROUND(M254-(H254*K254),2) -> 65.47 | O254: =IFERROR(N254/M254,0) -> 0.75548119 | P254: =IF(B254="","",TEXT(B254,"mmm-yyyy")) -> Jul-2025 | Q254: =IF(B254="","","Q"&ROUNDUP(MONTH(B254)/3,0)&"-"&YEAR(B254)) -> Q3-2025
A255: TXN-100254 | B255: 45705 | C255: East | D255: E-004 | E255: Grocery | F255: Granola Pack | G255: Non-Member | H255: 2 | I255: 24.91 | J255: 0.087 | K255: 15.44 | L255: No | M255: =ROUND(H255*I255*(1-J255),2) -> 45.49 | N255: =ROUND(M255-(H255*K255),2) -> 14.61 | O255: =IFERROR(N255/M255,0) -> 0.32116949 | P255: =IF(B255="","",TEXT(B255,"mmm-yyyy")) -> Feb-2025 | Q255: =IF(B255="","","Q"&ROUNDUP(MONTH(B255)/3,0)&"-"&YEAR(B255)) -> Q1-2025
A256: TXN-100255 | B256: 45794 | C256: West | D256: W-001 | E256: Electronics | F256: Laptop Stand | G256: Member | H256: 1 | I256: 164 | J256: 0.044 | K256: 130.38 | L256: No | M256: =ROUND(H256*I256*(1-J256),2) -> 156.78 | N256: =ROUND(M256-(H256*K256),2) -> 26.4 | O256: =IFERROR(N256/M256,0) -> 0.16838883 | P256: =IF(B256="","",TEXT(B256,"mmm-yyyy")) -> May-2025 | Q256: =IF(B256="","","Q"&ROUNDUP(MONTH(B256)/3,0)&"-"&YEAR(B256)) -> Q2-2025
A257: TXN-100256 | B257: 45722 | C257: East | D257: E-001 | E257: Electronics | F257: Laptop Stand | G257: Non-Member | H257: 3 | I257: 189.32 | J257: 0.102 | K257: 146.99 | L257: No | M257: =ROUND(H257*I257*(1-J257),2) -> 510.03 | N257: =ROUND(M257-(H257*K257),2) -> 69.06 | O257: =IFERROR(N257/M257,0) -> 0.1354038 | P257: =IF(B257="","",TEXT(B257,"mmm-yyyy")) -> Mar-2025 | Q257: =IF(B257="","","Q"&ROUNDUP(MONTH(B257)/3,0)&"-"&YEAR(B257)) -> Q1-2025
A258: TXN-100257 | B258: 45737 | C258: East | D258: E-009 | E258: Electronics | F258: Bluetooth Speaker | G258: Non-Member | H258: 6 | I258: 143.51 | J258: 0.094 | K258: 112.28 | L258: No | M258: =ROUND(H258*I258*(1-J258),2) -> 780.12 | N258: =ROUND(M258-(H258*K258),2) -> 106.44 | O258: =IFERROR(N258/M258,0) -> 0.13644055 | P258: =IF(B258="","",TEXT(B258,"mmm-yyyy")) -> Mar-2025 | Q258: =IF(B258="","","Q"&ROUNDUP(MONTH(B258)/3,0)&"-"&YEAR(B258)) -> Q1-2025
A259: TXN-100258 | B259: 45548 | C259: West | D259: W-006 | E259: Electronics | F259: Bluetooth Speaker | G259: Non-Member | H259: 3 | I259: 181.83 | J259: 0 | K259: 123.5 | L259: Yes | M259: =ROUND(H259*I259*(1-J259),2) -> 545.49 | N259: =ROUND(M259-(H259*K259),2) -> 174.99 | O259: =IFERROR(N259/M259,0) -> 0.32079415 | P259: =IF(B259="","",TEXT(B259,"mmm-yyyy")) -> Sep-2024 | Q259: =IF(B259="","","Q"&ROUNDUP(MONTH(B259)/3,0)&"-"&YEAR(B259)) -> Q3-2024
A260: TXN-100259 | B260: 45931 | C260: North | D260: N-007 | E260: Home Goods | F260: Storage Bin | G260: Non-Member | H260: 6 | I260: 32.38 | J260: 0.101 | K260: 16.14 | L260: No | M260: =ROUND(H260*I260*(1-J260),2) -> 174.66 | N260: =ROUND(M260-(H260*K260),2) -> 77.82 | O260: =IFERROR(N260/M260,0) -> 0.44555136 | P260: =IF(B260="","",TEXT(B260,"mmm-yyyy")) -> Oct-2025 | Q260: =IF(B260="","","Q"&ROUNDUP(MONTH(B260)/3,0)&"-"&YEAR(B260)) -> Q4-2025
A261: TXN-100260 | B261: 45439 | C261: North | D261: N-003 | E261: Beauty | F261: Sunscreen SPF50 | G261: Non-Member | H261: 8 | I261: 27.41 | J261: 0.067 | K261: 12.28 | L261: No | M261: =ROUND(H261*I261*(1-J261),2) -> 204.59 | N261: =ROUND(M261-(H261*K261),2) -> 106.35 | O261: =IFERROR(N261/M261,0) -> 0.51982013 | P261: =IF(B261="","",TEXT(B261,"mmm-yyyy")) -> May-2024 | Q261: =IF(B261="","","Q"&ROUNDUP(MONTH(B261)/3,0)&"-"&YEAR(B261)) -> Q2-2024
A262: TXN-100261 | B262: 45604 | C262: East | D262: E-013 | E262: Electronics | F262: Power Bank | G262: Member | H262: 9 | I262: 162.52 | J262: 0 | K262: 106.74 | L262: No | M262: =ROUND(H262*I262*(1-J262),2) -> 1462.68 | N262: =ROUND(M262-(H262*K262),2) -> 502.02 | O262: =IFERROR(N262/M262,0) -> 0.3432193 | P262: =IF(B262="","",TEXT(B262,"mmm-yyyy")) -> Nov-2024 | Q262: =IF(B262="","","Q"&ROUNDUP(MONTH(B262)/3,0)&"-"&YEAR(B262)) -> Q4-2024
A263: TXN-100262 | B263: 45657 | C263: East | D263: E-013 | E263: Home Goods | F263: Bath Towel Set | G263: Non-Member | H263: 2 | I263: 81.45 | J263: 0.119 | K263: 30.22 | L263: Yes | M263: =ROUND(H263*I263*(1-J263),2) -> 143.51 | N263: =ROUND(M263-(H263*K263),2) -> 83.07 | O263: =IFERROR(N263/M263,0) -> 0.57884468 | P263: =IF(B263="","",TEXT(B263,"mmm-yyyy")) -> Dec-2024 | Q263: =IF(B263="","","Q"&ROUNDUP(MONTH(B263)/3,0)&"-"&YEAR(B263)) -> Q4-2024
A264: TXN-100263 | B264: 45703 | C264: East | D264: E-003 | E264: Apparel | F264: Casual Dress | G264: Member | H264: 1 | I264: 92.63 | J264: 0.04 | K264: 41.21 | L264: No | M264: =ROUND(H264*I264*(1-J264),2) -> 88.92 | N264: =ROUND(M264-(H264*K264),2) -> 47.71 | O264: =IFERROR(N264/M264,0) -> 0.53654971 | P264: =IF(B264="","",TEXT(B264,"mmm-yyyy")) -> Feb-2025 | Q264: =IF(B264="","","Q"&ROUNDUP(MONTH(B264)/3,0)&"-"&YEAR(B264)) -> Q1-2025
... A335: TXN-100334 | B335: 45621 | C335: West | D335: W-011 | E335: Beauty | F335: Lipstick | G335: Non-Member | H335: 1 | I335: 46.47 | J335: 0.09 | K335: 19.45 | L335: No | M335: =ROUND(H335*I335*(1-J335),2) -> 42.29 | N335: =ROUND(M335-(H335*K335),2) -> 22.84 | O335: =IFERROR(N335/M335,0) -> 0.5400804 | P335: =IF(B335="","",TEXT(B335,"mmm-yyyy")) -> Nov-2024 | Q335: =IF(B335="","","Q"&ROUNDUP(MONTH(B335)/3,0)&"-"&YEAR(B335)) -> Q4-2024
A336: TXN-100335 | C336: North | D336: N-009 | E336: Grocery | F336: Olive Oil 500ml | G336: Non-Member | H336: 2 | I336: 4.18 | J336: 0.015 | K336: 2.57 | L336: Yes | M336: =ROUND(H336*I336*(1-J336),2) -> 8.23 | N336: =ROUND(M336-(H336*K336),2) -> 3.09 | O336: =IFERROR(N336/M336,0) -> 0.37545565
A337: TXN-100336 | B337: 45728 | C337: East | D337: E-010 | E337: Grocery | F337: Sparkling Water 12pk | G337: Member | H337: 1 | I337: 11.73 | J337: 0.024 | K337: 7.81 | L337: No | M337: =ROUND(H337*I337*(1-J337),2) -> 11.45 | N337: =ROUND(M337-(H337*K337),2) -> 3.64 | O337: =IFERROR(N337/M337,0) -> 0.31790393 | P337: =IF(B337="","",TEXT(B337,"mmm-yyyy")) -> Mar-2025 | Q337: =IF(B337="","","Q"&ROUNDUP(MONTH(B337)/3,0)&"-"&YEAR(B337)) -> Q1-2025
A338: TXN-100337 | B338: 45521 | C338: East | D338: E-013 | E338: Beauty | F338: Sunscreen SPF50 | G338: Member | H338: 4 | I338: 19.86 | J338: 0.132 | K338: 12.77 | L338: No | M338: =ROUND(H338*I338*(1-J338),2) -> 68.95 | N338: =ROUND(M338-(H338*K338),2) -> 17.87 | O338: =IFERROR(N338/M338,0) -> 0.25917331 | P338: =IF(B338="","",TEXT(B338,"mmm-yyyy")) -> Aug-2024 | Q338: =IF(B338="","","Q"&ROUNDUP(MONTH(B338)/3,0)&"-"&YEAR(B338)) -> Q3-2024
A339: TXN-100338 | B339: 46001 | C339: South | D339: S-011 | E339: Home Goods | F339: Bath Towel Set | G339: Non-Member | H339: 4 | I339: 59.49 | J339: 0.31 | K339: 27.94 | L339: No | M339: =ROUND(H339*I339*(1-J339),2) -> 164.19 | N339: =ROUND(M339-(H339*K339),2) -> 52.43 | O339: =IFERROR(N339/M339,0) -> 0.31932517 | P339: =IF(B339="","",TEXT(B339,"mmm-yyyy")) -> Dec-2025 | Q339: =IF(B339="","","Q"&ROUNDUP(MONTH(B339)/3,0)&"-"&YEAR(B339)) -> Q4-2025
A340: TXN-100339 | B340: 45711 | C340: North | D340: N-005 | E340: Electronics | F340: Wireless Earbuds | G340: Member | H340: 2 | I340: 228.41 | J340: 0.073 | K340: 159.32 | L340: No | M340: =ROUND(H340*I340*(1-J340),2) -> 423.47 | N340: =ROUND(M340-(H340*K340),2) -> 104.83 | O340: =IFERROR(N340/M340,0) -> 0.24755 | P340: =IF(B340="","",TEXT(B340,"mmm-yyyy")) -> Feb-2025 | Q340: =IF(B340="","","Q"&ROUNDUP(MONTH(B340)/3,0)&"-"&YEAR(B340)) -> Q1-2025
A341: TXN-100340 | B341: 45607 | C341: North | D341: N-005 | E341: Home Goods | F341: LED Desk Lamp | G341: Non-Member | H341: 9 | I341: 16.98 | J341: 0.055 | K341: 7.04 | L341: No | M341: =ROUND(H341*I341*(1-J341),2) -> 144.41 | N341: =ROUND(M341-(H341*K341),2) -> 81.05 | O341: =IFERROR(N341/M341,0) -> 0.56124922 | P341: =IF(B341="","",TEXT(B341,"mmm-yyyy")) -> Nov-2024 | Q341: =IF(B341="","","Q"&ROUNDUP(MONTH(B341)/3,0)&"-"&YEAR(B341)) -> Q4-2024
A342: TXN-100341 | B342: 45906 | C342: West | D342: W-002 | E342: Electronics | F342: Smart Watch | G342: Non-Member | H342: 1 | I342: 177.41 | J342: 0.077 | K342: 131.2 | L342: No | M342: =ROUND(H342*I342*(1-J342),2) -> 163.75 | N342: =ROUND(M342-(H342*K342),2) -> 32.55 | O342: =IFERROR(N342/M342,0) -> 0.19877863 | P342: =IF(B342="","",TEXT(B342,"mmm-yyyy")) -> Sep-2025 | Q342: =IF(B342="","","Q"&ROUNDUP(MONTH(B342)/3,0)&"-"&YEAR(B342)) -> Q3-2025
A343: TXN-100342 | B343: 45761 | C343: West | D343: W-001 | E343: Apparel | F343: Running Shoes | G343: Non-Member | H343: 3 | I343: 96.81 | J343: 0.105 | K343: 49.25 | L343: No | M343: =ROUND(H343*I343*(1-J343),2) -> 259.93 | N343: =ROUND(M343-(H343*K343),2) -> 112.18 | O343: =IFERROR(N343/M343,0) -> 0.43157773 | P343: =IF(B343="","",TEXT(B343,"mmm-yyyy")) -> Apr-2025 | Q343: =IF(B343="","","Q"&ROUNDUP(MONTH(B343)/3,0)&"-"&YEAR(B343)) -> Q2-2025
A344: TXN-100343 | B344: 45735 | C344: South | D344: S-010 | E344: Home Goods | F344: Bath Towel Set | G344: Member | H344: 1 | I344: 23.56 | J344: 0.159 | K344: 9.2 | L344: No | M344: =ROUND(H344*I344*(1-J344),2) -> 19.81 | N344: =ROUND(M344-(H344*K344),2) -> 10.61 | O344: =IFERROR(N344/M344,0) -> 0.53558809 | P344: =IF(B344="","",TEXT(B344,"mmm-yyyy")) -> Mar-2025 | Q344: =IF(B344="","","Q"&ROUNDUP(MONTH(B344)/3,0)&"-"&YEAR(B344)) -> Q1-2025
A345: TXN-100344 | B345: 45592 | C345: South | D345: S-002 | E345: Electronics | F345: Smart Watch | G345: Member | H345: 13 | I345: 140.8 | J345: 0.244 | K345: 101.75 | L345: No | M345: =ROUND(H345*I345*(1-J345),2) -> 1383.78 | N345: =ROUND(M345-(H345*K345),2) -> 61.03 | O345: =IFERROR(N345/M345,0) -> 0.044103832 | P345: =IF(B345="","",TEXT(B345,"mmm-yyyy")) -> Oct-2024 | Q345: =IF(B345="","","Q"&ROUNDUP(MONTH(B345)/3,0)&"-"&YEAR(B345)) -> Q4-2024
A346: TXN-100345 | B346: 45982 | C346: East | D346: E-004 | E346: Grocery | F346: Granola Pack | G346: Member | H346: 6 | I346: 7.3 | J346: 0.18 | K346: 4.13 | L346: No | M346: =ROUND(H346*I346*(1-J346),2) -> 35.92 | N346: =ROUND(M346-(H346*K346),2) -> 11.14 | O346: =IFERROR(N346/M346,0) -> 0.31013363 | P346: =IF(B346="","",TEXT(B346,"mmm-yyyy")) -> Nov-2025 | Q346: =IF(B346="","","Q"&ROUNDUP(MONTH(B346)/3,0)&"-"&YEAR(B346)) -> Q4-2025
A347: TXN-100346 | B347: 45746 | C347: West | D347: W-006 | E347: Beauty | F347: Sunscreen SPF50 | G347: Member | H347: 6 | I347: 49.81 | J347: 0.081 | K347: 17.41 | L347: No | M347: =ROUND(H347*I347*(1-J347),2) -> 274.65 | N347: =ROUND(M347-(H347*K347),2) -> 170.19 | O347: =IFERROR(N347/M347,0) -> 0.61966139 | P347: =IF(B347="","",TEXT(B347,"mmm-yyyy")) -> Mar-2025 | Q347: =IF(B347="","","Q"&ROUNDUP(MONTH(B347)/3,0)&"-"&YEAR(B347)) -> Q1-2025
A348: TXN-100347 | B348: 45494 | C348: South | D348: S-005 | E348: Apparel | F348: Women's Jeans | G348: Member | H348: 8 | I348: 65.3 | J348: 0.198 | K348: 27.86 | L348: Yes | M348: =ROUND(H348*I348*(1-J348),2) -> 418.96 | N348: =ROUND(M348-(H348*K348),2) -> 196.08 | O348: =IFERROR(N348/M348,0) -> 0.46801604 | P348: =IF(B348="","",TEXT(B348,"mmm-yyyy")) -> Jul-2024 | Q348: =IF(B348="","","Q"&ROUNDUP(MONTH(B348)/3,0)&"-"&YEAR(B348)) -> Q3-2024
... A388: TXN-100387 | B388: 45731 | C388: South | D388: S-010 | E388: Beauty | F388: Lipstick | G388: Member | H388: 4 | I388: 54.5 | J388: 0.124 | K388: 22.58 | L388: No | M388: =ROUND(H388*I388*(1-J388),2) -> 190.97 | N388: =ROUND(M388-(H388*K388),2) -> 100.65 | O388: =IFERROR(N388/M388,0) -> 0.52704613 | P388: =IF(B388="","",TEXT(B388,"mmm-yyyy")) -> Mar-2025 | Q388: =IF(B388="","","Q"&ROUNDUP(MONTH(B388)/3,0)&"-"&YEAR(B388)) -> Q1-2025
A389: TXN-100388 | C389: West | D389: W-001 | E389: Electronics | F389: Wireless Earbuds | G389: Non-Member | H389: 1 | I389: 146.35 | J389: 0.11 | K389: 95.14 | L389: No | M389: =ROUND(H389*I389*(1-J389),2) -> 130.25 | N389: =ROUND(M389-(H389*K389),2) -> 35.11 | O389: =IFERROR(N389/M389,0) -> 0.26955854
A390: TXN-100389 | B390: 45677 | C390: South | D390: S-012 | E390: Beauty | F390: Lipstick | G390: Member | H390: 1 | I390: 16.27 | J390: 0.191 | K390: 7.16 | L390: No | M390: =ROUND(H390*I390*(1-J390),2) -> 13.16 | N390: =ROUND(M390-(H390*K390),2) -> 6 | O390: =IFERROR(N390/M390,0) -> 0.45592705 | P390: =IF(B390="","",TEXT(B390,"mmm-yyyy")) -> Jan-2025 | Q390: =IF(B390="","","Q"&ROUNDUP(MONTH(B390)/3,0)&"-"&YEAR(B390)) -> Q1-2025
A391: TXN-100390 | B391: 45734 | C391: East | D391: E-005 | E391: Electronics | F391: Wireless Earbuds | G391: Non-Member | H391: 1 | I391: 39.24 | J391: 0.076 | K391: 29.19 | L391: No | M391: =ROUND(H391*I391*(1-J391),2) -> 36.26 | N391: =ROUND(M391-(H391*K391),2) -> 7.07 | O391: =IFERROR(N391/M391,0) -> 0.19498069 | P391: =IF(B391="","",TEXT(B391,"mmm-yyyy")) -> Mar-2025 | Q391: =IF(B391="","","Q"&ROUNDUP(MONTH(B391)/3,0)&"-"&YEAR(B391)) -> Q1-2025
A392: TXN-100391 | B392: 45645 | C392: South | D392: S-007 | E392: Grocery | F392: Organic Coffee 12oz | G392: Member | H392: 1 | I392: 13.49 | J392: 0.367 | K392: 7.69 | L392: No | M392: =ROUND(H392*I392*(1-J392),2) -> 8.54 | N392: =ROUND(M392-(H392*K392),2) -> 0.85 | O392: =IFERROR(N392/M392,0) -> 0.099531616 | P392: =IF(B392="","",TEXT(B392,"mmm-yyyy")) -> Dec-2024 | Q392: =IF(B392="","","Q"&ROUNDUP(MONTH(B392)/3,0)&"-"&YEAR(B392)) -> Q4-2024
A393: TXN-100392 | B393: 45786 | C393: West | D393: W-001 | E393: Electronics | F393: Smart Watch | G393: Member | H393: 2 | I393: 249.7 | J393: 0.122 | K393: 113.01 | L393: No | M393: =ROUND(H393*I393*(1-J393),2) -> 438.47 | N393: =ROUND(M393-(H393*K393),2) -> 212.45 | O393: =IFERROR(N393/M393,0) -> 0.48452574 | P393: =IF(B393="","",TEXT(B393,"mmm-yyyy")) -> May-2025 | Q393: =IF(B393="","","Q"&ROUNDUP(MONTH(B393)/3,0)&"-"&YEAR(B393)) -> Q2-2025
A394: TXN-100393 | B394: 45508 | C394: South | D394: S-008 | E394: Electronics | F394: Laptop Stand | G394: Member | H394: 6 | I394: 49.57 | J394: 0.191 | K394: 38.21 | L394: No | M394: =ROUND(H394*I394*(1-J394),2) -> 240.61 | N394: =ROUND(M394-(H394*K394),2) -> 11.35 | O394: =IFERROR(N394/M394,0) -> 0.047171772 | P394: =IF(B394="","",TEXT(B394,"mmm-yyyy")) -> Aug-2024 | Q394: =IF(B394="","","Q"&ROUNDUP(MONTH(B394)/3,0)&"-"&YEAR(B394)) -> Q3-2024
A395: TXN-100394 | B395: 45923 | C395: East | D395: E-015 | E395: Apparel | F395: Running Shoes | G395: Member | H395: 11 | I395: 96.21 | J395: 0.161 | K395: 49.35 | L395: No | M395: =ROUND(H395*I395*(1-J395),2) -> 887.92 | N395: =ROUND(M395-(H395*K395),2) -> 345.07 | O395: =IFERROR(N395/M395,0) -> 0.38862735 | P395: =IF(B395="","",TEXT(B395,"mmm-yyyy")) -> Sep-2025 | Q395: =IF(B395="","","Q"&ROUNDUP(MONTH(B395)/3,0)&"-"&YEAR(B395)) -> Q3-2025
A396: TXN-100395 | B396: 45985 | C396: South | D396: S-002 | E396: Home Goods | F396: Throw Pillow | G396: Member | H396: 4 | I396: 23.13 | J396: 0.132 | K396: 9.31 | L396: No | M396: =ROUND(H396*I396*(1-J396),2) -> 80.31 | N396: =ROUND(M396-(H396*K396),2) -> 43.07 | O396: =IFERROR(N396/M396,0) -> 0.53629685 | P396: =IF(B396="","",TEXT(B396,"mmm-yyyy")) -> Nov-2025 | Q396: =IF(B396="","","Q"&ROUNDUP(MONTH(B396)/3,0)&"-"&YEAR(B396)) -> Q4-2025
A397: TXN-100396 | B397: 45769 | C397: South | D397: S-015 | E397: Apparel | F397: Running Shoes | G397: Member | H397: 1 | I397: 105.3 | J397: 0 | K397: 43.49 | L397: No | M397: =ROUND(H397*I397*(1-J397),2) -> 105.3 | N397: =ROUND(M397-(H397*K397),2) -> 61.81 | O397: =IFERROR(N397/M397,0) -> 0.58698955 | P397: =IF(B397="","",TEXT(B397,"mmm-yyyy")) -> Apr-2025 | Q397: =IF(B397="","","Q"&ROUNDUP(MONTH(B397)/3,0)&"-"&YEAR(B397)) -> Q2-2025
A398: TXN-100397 | B398: 45688 | C398: North | D398: N-010 | E398: Grocery | F398: Olive Oil 500ml | G398: Member | H398: 2 | I398: 24.19 | J398: 0.104 | K398: 14.45 | L398: No | M398: =ROUND(H398*I398*(1-J398),2) -> 43.35 | N398: =ROUND(M398-(H398*K398),2) -> 14.45 | O398: =IFERROR(N398/M398,0) -> 0.33333333 | P398: =IF(B398="","",TEXT(B398,"mmm-yyyy")) -> Jan-2025 | Q398: =IF(B398="","","Q"&ROUNDUP(MONTH(B398)/3,0)&"-"&YEAR(B398)) -> Q1-2025
A399: TXN-100398 | B399: 45849 | C399: East | D399: E-011 | E399: Electronics | F399: Power Bank | G399: Member | H399: 4 | I399: 190.27 | J399: 0.141 | K399: 144.26 | L399: No | M399: =ROUND(H399*I399*(1-J399),2) -> 653.77 | N399: =ROUND(M399-(H399*K399),2) -> 76.73 | O399: =IFERROR(N399/M399,0) -> 0.11736543 | P399: =IF(B399="","",TEXT(B399,"mmm-yyyy")) -> Jul-2025 | Q399: =IF(B399="","","Q"&ROUNDUP(MONTH(B399)/3,0)&"-"&YEAR(B399)) -> Q3-2025
A400: TXN-100399 | B400: 45472 | C400: North | D400: N-014 | E400: Beauty | F400: Lipstick | G400: Member | H400: 1 | I400: 18.68 | J400: 0.047 | K400: 7.3 | L400: No | M400: =ROUND(H400*I400*(1-J400),2) -> 17.8 | N400: =ROUND(M400-(H400*K400),2) -> 10.5 | O400: =IFERROR(N400/M400,0) -> 0.58988764 | P400: =IF(B400="","",TEXT(B400,"mmm-yyyy")) -> Jun-2024 | Q400: =IF(B400="","","Q"&ROUNDUP(MONTH(B400)/3,0)&"-"&YEAR(B400)) -> Q2-2024
A401: TXN-100400 | B401: 45915 | C401: West | D401: W-005 | E401: Grocery | F401: Snack Box | G401: Member | H401: 2 | I401: 13.89 | J401: 0.054 | K401: 7.87 | L401: No | M401: =ROUND(H401*I401*(1-J401),2) -> 26.28 | N401: =ROUND(M401-(H401*K401),2) -> 10.54 | O401: =IFERROR(N401/M401,0) -> 0.40106545 | P401: =IF(B401="","",TEXT(B401,"mmm-yyyy")) -> Sep-2025 | Q401: =IF(B401="","","Q"&ROUNDUP(MONTH(B401)/3,0)&"-"&YEAR(B401)) -> Q3-2025
... A457: TXN-100456 | B457: 45729 | C457: North | D457: N-006 | E457: Apparel | F457: Men's T-Shirt | G457: Member | H457: 4 | I457: 90.64 | J457: 0.164 | K457: 36.91 | L457: No | M457: =ROUND(H457*I457*(1-J457),2) -> 303.1 | N457: =ROUND(M457-(H457*K457),2) -> 155.46 | O457: =IFERROR(N457/M457,0) -> 0.51290003 | P457: =IF(B457="","",TEXT(B457,"mmm-yyyy")) -> Mar-2025 | Q457: =IF(B457="","","Q"&ROUNDUP(MONTH(B457)/3,0)&"-"&YEAR(B457)) -> Q1-2025
A458: TXN-100457 | C458: West | D458: W-003 | E458: Beauty | F458: Sunscreen SPF50 | G458: Member | H458: 1 | I458: 53.85 | J458: 0.135 | K458: 18.99 | L458: No | M458: =ROUND(H458*I458*(1-J458),2) -> 46.58 | N458: =ROUND(M458-(H458*K458),2) -> 27.59 | O458: =IFERROR(N458/M458,0) -> 0.5923143
A459: TXN-100458 | B459: 45632 | C459: West | D459: W-013 | E459: Beauty | F459: Shampoo 300ml | G459: Member | H459: 3 | I459: 11.83 | J459: 0.184 | K459: 5.05 | L459: No | M459: =ROUND(H459*I459*(1-J459),2) -> 28.96 | N459: =ROUND(M459-(H459*K459),2) -> 13.81 | O459: =IFERROR(N459/M459,0) -> 0.47686464 | P459: =IF(B459="","",TEXT(B459,"mmm-yyyy")) -> Dec-2024 | Q459: =IF(B459="","","Q"&ROUNDUP(MONTH(B459)/3,0)&"-"&YEAR(B459)) -> Q4-2024
A460: TXN-100459 | B460: 45600 | C460: East | D460: E-005 | E460: Beauty | F460: Face Moisturizer | G460: Member | H460: 1 | I460: 54.17 | J460: 0.09 | K460: 17.56 | L460: No | M460: =ROUND(H460*I460*(1-J460),2) -> 49.29 | N460: =ROUND(M460-(H460*K460),2) -> 31.73 | O460: =IFERROR(N460/M460,0) -> 0.64374112 | P460: =IF(B460="","",TEXT(B460,"mmm-yyyy")) -> Nov-2024 | Q460: =IF(B460="","","Q"&ROUNDUP(MONTH(B460)/3,0)&"-"&YEAR(B460)) -> Q4-2024
A461: TXN-100460 | B461: 45460 | C461: North | D461: N-006 | E461: Grocery | F461: Sparkling Water 12pk | G461: Member | H461: 4 | I461: 22.65 | J461: 0.025 | K461: 14.85 | L461: No | M461: =ROUND(H461*I461*(1-J461),2) -> 88.34 | N461: =ROUND(M461-(H461*K461),2) -> 28.94 | O461: =IFERROR(N461/M461,0) -> 0.32759792 | P461: =IF(B461="","",TEXT(B461,"mmm-yyyy")) -> Jun-2024 | Q461: =IF(B461="","","Q"&ROUNDUP(MONTH(B461)/3,0)&"-"&YEAR(B461)) -> Q2-2024
A462: TXN-100461 | B462: 45627 | C462: South | D462: S-010 | E462: Beauty | F462: Shampoo 300ml | G462: Member | H462: 5 | I462: 25.22 | J462: 0.111 | K462: 11.25 | L462: No | M462: =ROUND(H462*I462*(1-J462),2) -> 112.1 | N462: =ROUND(M462-(H462*K462),2) -> 55.85 | O462: =IFERROR(N462/M462,0) -> 0.49821588 | P462: =IF(B462="","",TEXT(B462,"mmm-yyyy")) -> Dec-2024 | Q462: =IF(B462="","","Q"&ROUNDUP(MONTH(B462)/3,0)&"-"&YEAR(B462)) -> Q4-2024
A463: TXN-100462 | B463: 45617 | C463: East | D463: E-011 | E463: Apparel | F463: Women's Jeans | G463: Member | H463: 2 | I463: 56.25 | J463: 0.029 | K463: 27.14 | L463: No | M463: =ROUND(H463*I463*(1-J463),2) -> 109.24 | N463: =ROUND(M463-(H463*K463),2) -> 54.96 | O463: =IFERROR(N463/M463,0) -> 0.50311241 | P463: =IF(B463="","",TEXT(B463,"mmm-yyyy")) -> Nov-2024 | Q463: =IF(B463="","","Q"&ROUNDUP(MONTH(B463)/3,0)&"-"&YEAR(B463)) -> Q4-2024
A464: TXN-100463 | B464: 45906 | C464: North | D464: N-006 | E464: Electronics | F464: Bluetooth Speaker | G464: Non-Member | H464: 9 | I464: 106 | J464: 0.054 | K464: 79.43 | L464: No | M464: =ROUND(H464*I464*(1-J464),2) -> 902.48 | N464: =ROUND(M464-(H464*K464),2) -> 187.61 | O464: =IFERROR(N464/M464,0) -> 0.20788272 | P464: =IF(B464="","",TEXT(B464,"mmm-yyyy")) -> Sep-2025 | Q464: =IF(B464="","","Q"&ROUNDUP(MONTH(B464)/3,0)&"-"&YEAR(B464)) -> Q3-2025
A465: TXN-100464 | B465: 45817 | C465: South | D465: S-002 | E465: Electronics | F465: Wireless Earbuds | G465: Member | H465: 2 | I465: 200.5 | J465: 0.257 | K465: 159.71 | L465: No | M465: =ROUND(H465*I465*(1-J465),2) -> 297.94 | N465: =ROUND(M465-(H465*K465),2) -> -21.48 | O465: =IFERROR(N465/M465,0) -> -0.072095053 | P465: =IF(B465="","",TEXT(B465,"mmm-yyyy")) -> Jun-2025 | Q465: =IF(B465="","","Q"&ROUNDUP(MONTH(B465)/3,0)&"-"&YEAR(B465)) -> Q2-2025
A466: TXN-100465 | B466: 45847 | C466: North | D466: N-005 | E466: Grocery | F466: Granola Pack | G466: Member | H466: 1 | I466: 13.76 | J466: 0 | K466: 8.93 | L466: No | M466: =ROUND(H466*I466*(1-J466),2) -> 13.76 | N466: =ROUND(M466-(H466*K466),2) -> 4.83 | O466: =IFERROR(N466/M466,0) -> 0.35101744 | P466: =IF(B466="","",TEXT(B466,"mmm-yyyy")) -> Jul-2025 | Q466: =IF(B466="","","Q"&ROUNDUP(MONTH(B466)/3,0)&"-"&YEAR(B466)) -> Q3-2025
A467: TXN-100466 | B467: 45628 | C467: West | D467: W-003 | E467: Apparel | F467: Running Shoes | G467: Member | H467: 3 | I467: 61.81 | J467: 0.1 | K467: 27.17 | L467: No | M467: =ROUND(H467*I467*(1-J467),2) -> 166.89 | N467: =ROUND(M467-(H467*K467),2) -> 85.38 | O467: =IFERROR(N467/M467,0) -> 0.51159446 | P467: =IF(B467="","",TEXT(B467,"mmm-yyyy")) -> Dec-2024 | Q467: =IF(B467="","","Q"&ROUNDUP(MONTH(B467)/3,0)&"-"&YEAR(B467)) -> Q4-2024
A468: TXN-100467 | B468: 45558 | C468: South | D468: S-014 | E468: Apparel | F468: Men's T-Shirt | G468: Member | H468: 10 | I468: 30.87 | J468: 0.198 | K468: 15.57 | L468: No | M468: =ROUND(H468*I468*(1-J468),2) -> 247.58 | N468: =ROUND(M468-(H468*K468),2) -> 91.88 | O468: =IFERROR(N468/M468,0) -> 0.37111237 | P468: =IF(B468="","",TEXT(B468,"mmm-yyyy")) -> Sep-2024 | Q468: =IF(B468="","","Q"&ROUNDUP(MONTH(B468)/3,0)&"-"&YEAR(B468)) -> Q3-2024
A469: TXN-100468 | B469: 45381 | C469: East | D469: E-013 | E469: Home Goods | F469: Storage Bin | G469: Member | H469: 7 | I469: 28.2 | J469: 0.135 | K469: 10.13 | L469: No | M469: =ROUND(H469*I469*(1-J469),2) -> 170.75 | N469: =ROUND(M469-(H469*K469),2) -> 99.84 | O469: =IFERROR(N469/M469,0) -> 0.58471449 | P469: =IF(B469="","",TEXT(B469,"mmm-yyyy")) -> Mar-2024 | Q469: =IF(B469="","","Q"&ROUNDUP(MONTH(B469)/3,0)&"-"&YEAR(B469)) -> Q1-2024
A470: TXN-100469 | B470: 45534 | C470: West | D470: W-009 | E470: Grocery | F470: Granola Pack | G470: Member | H470: 3 | I470: 15.6 | J470: 0.076 | K470: 9.13 | L470: No | M470: =ROUND(H470*I470*(1-J470),2) -> 43.24 | N470: =ROUND(M470-(H470*K470),2) -> 15.85 | O470: =IFERROR(N470/M470,0) -> 0.36655874 | P470: =IF(B470="","",TEXT(B470,"mmm-yyyy")) -> Aug-2024 | Q470: =IF(B470="","","Q"&ROUNDUP(MONTH(B470)/3,0)&"-"&YEAR(B470)) -> Q3-2024
... A493: TXN-100492 | B493: 45644 | C493: East | D493: E-004 | E493: Home Goods | F493: Storage Bin | G493: Member | H493: 4 | I493: 41.77 | J493: 0.092 | K493: 15.26 | L493: No | M493: =ROUND(H493*I493*(1-J493),2) -> 151.71 | N493: =ROUND(M493-(H493*K493),2) -> 90.67 | O493: =IFERROR(N493/M493,0) -> 0.59765342 | P493: =IF(B493="","",TEXT(B493,"mmm-yyyy")) -> Dec-2024 | Q493: =IF(B493="","","Q"&ROUNDUP(MONTH(B493)/3,0)&"-"&YEAR(B493)) -> Q4-2024
A494: TXN-100493 | C494: East | D494: E-009 | E494: Grocery | F494: Sparkling Water 12pk | G494: Member | H494: 3 | I494: 9.22 | J494: 0.091 | K494: 6.02 | L494: No | M494: =ROUND(H494*I494*(1-J494),2) -> 25.14 | N494: =ROUND(M494-(H494*K494),2) -> 7.08 | O494: =IFERROR(N494/M494,0) -> 0.28162291
A495: TXN-100494 | B495: 45899 | C495: East | D495: E-005 | E495: Grocery | F495: Olive Oil 500ml | G495: Non-Member | H495: 7 | I495: 8.75 | J495: 0.016 | K495: 5.75 | L495: No | M495: =ROUND(H495*I495*(1-J495),2) -> 60.27 | N495: =ROUND(M495-(H495*K495),2) -> 20.02 | O495: =IFERROR(N495/M495,0) -> 0.33217189 | P495: =IF(B495="","",TEXT(B495,"mmm-yyyy")) -> Aug-2025 | Q495: =IF(B495="","","Q"&ROUNDUP(MONTH(B495)/3,0)&"-"&YEAR(B495)) -> Q3-2025
...

Sheet KPI_Definitions
A1: KPI Name | B1: Formula/Logic | C1: Business Reason | D1: Target/Benchmark
A2: Total Revenue | B2: SUM of Revenue column | C2: Top-line performance | D2: Track growth vs prior period
A3: Net Margin % | B3: GrossProfit ÷ Revenue | C3: Core profitability health — your main business question | D3: Company target: 8%+ (currently ~6.5%, per Phase 1 brief)
A4: Discount Rate | B4: AVERAGE of DiscountPct | C4: Detects over-discounting, root cause candidate | D4: Flag if >15% average
A5: Return Rate | B5: Returned="Yes" ÷ Total transactions | C5: Detects hidden cost center | D5: Flag if >10%
A6: Loss-Making Transaction % | B6: COUNTIF NetMarginPct<0 ÷ Total | C6: Direct measure of your Key Finding #1 | D6: Target: <1%
A7: Revenue by Region | B7: SUMIFS by Region | C7: Identifies regional performance gaps | D7: Compare South vs other regions
A8: Revenue by Category | B8: SUMIFS by Category | C8: Identifies category performance gaps | D8: Compare Electronics vs other categories

Sheet Insight_Workings
A1: Region | B1: Loss-Making Transactions
A2: North | B2: =COUNTIFS('Cleaned Data'!C2:C6501,"North",'Cleaned Data'!O2:O6501,"<0") -> 3
A3: South | B3: =COUNTIFS('Cleaned Data'!C2:C6501,"South",'Cleaned Data'!O2:O6501,"<0") -> 111
A4: East | B4: =COUNTIFS('Cleaned Data'!C2:C6501,"East",'Cleaned Data'!O2:O6501,"<0") -> 1
A5: West | B5: =COUNTIFS('Cleaned Data'!C2:C6501,"West",'Cleaned Data'!O2:O6501,"<0") -> 0
A7: Electronics | B7: =COUNTIFS('Cleaned Data'!E2:E6501,"Electronics",'Cleaned Data'!O2:O6501,"<0") -> 101
A8: Apparel | B8: =COUNTIFS('Cleaned Data'!E2:E6501,"Apparel",'Cleaned Data'!O2:O6501,"<0") -> 0
A9: Home Goods | B9: =COUNTIFS('Cleaned Data'!E2:E6501,"Home Goods",'Cleaned Data'!O2:O6501,"<0") -> 3
A10: Grocery | B10: =COUNTIFS('Cleaned Data'!E2:E6501,"Grocery",'Cleaned Data'!O2:O6501,"<0") -> 11
A11: Beauty | B11: =COUNTIFS('Cleaned Data'!E2:E6501,"Beauty",'Cleaned Data'!O2:O6501,"<0") -> 0
A12: Total loss count | B12: =COUNTIF('Cleaned Data'!O2:O6501,"<0") -> 115
A13: Overall loss transaction pct | B13: =COUNTIF('Cleaned Data'!O2:O6501,"<0")/COUNTA('Cleaned Data'!A2:A6501) -> 0.017692308
A14: Electronics and south | B14: =COUNTIFS('Cleaned Data'!C2:C6501,"South",'Cleaned Data'!E2:E6501,"Electronics",'Cleaned Data'!O2:O6501,"<0") -> 99
A15: Discount given for Electronics x South | B15: =AVERAGEIFS('Cleaned Data'!J2:J6501,'Cleaned Data'!C2:C6501,"South",'Cleaned Data'!E2:E6501,"Electronics") -> 0.21717287
A16: Average discount of all transaction | B16: =AVERAGE('Cleaned Data'!J2:J6501) -> 0.112392

Sheet Pivot_MarginByRegionCat
A1: Row Labels | B1: Avg Net Margin%
A2: East | B2: 0.41371915
A3: Apparel | B3: 0.4766975
A4: Beauty | B4: 0.58183896
A5: Electronics | B5: 0.21761215
A6: Grocery | B6: 0.31914878
A7: Home Goods | B7: 0.54501664
A8: North | B8: 0.40638773
A9: Apparel | B9: 0.48275767
A10: Beauty | B10: 0.59006615
A11: Electronics | B11: 0.21299228
A12: Grocery | B12: 0.3065816
A13: Home Goods | B13: 0.53521511
... A26: Grand Total | B26: 0.38775664

Sheet Pivot_DiscountByRegionCat
A1: Row Labels | B1: Average of DiscountPct
A2: East | B2: 0.079939729
A3: Apparel | B3: 0.08104918
A4: Beauty | B4: 0.088024476
A5: Electronics | B5: 0.078146835
A6: Grocery | B6: 0.076678899
A7: Home Goods | B7: 0.077140575
A8: North | B8: 0.079251852
A9: Apparel | B9: 0.076066667
A10: Beauty | B10: 0.078349359
A11: Electronics | B11: 0.080430556
A12: Grocery | B12: 0.080648387
A13: Home Goods | B13: 0.080360902
... A26: Grand Total | B26: 0.112392

Sheet _x0009_Pivot_MonthlyTrend
A1: Row Labels | B1: Sum of Revenue | C1: Average of NetMarginPct
A2: 2024 | B2: 515335.49 | C2: 0.40554731
A3: Jan | B3: 2486.58 | C3: 0.40590291
A4: Feb | B4: 7656.62 | C4: 0.38445538
A5: Mar | B5: 12624.82 | C5: 0.4232517
A6: Apr | B6: 21876.66 | C6: 0.40881433
A7: May | B7: 28051.92 | C7: 0.40368985
A8: Jun | B8: 39961.96 | C8: 0.41768678
A9: Jul | B9: 43670.51 | C9: 0.42705217
A10: Aug | B10: 65148.8 | C10: 0.39841808
A11: Sep | B11: 71688.68 | C11: 0.39398458
A12: Oct | B12: 64763.79 | C12: 0.39137485
A13: Nov | B13: 72816.87 | C13: 0.40314654
... A28: Grand Total | B28: 1639357.5 | C28: 0.38780221

Sheet Forecast_Data
A1: Date | B1: Revenue_Actual | C1: Month_Index | D1: Linear_Forecast | E1: Seasonally-Adjusted Forecast
A2: 45292 | B2: 2486.58 | C2: 1
A3: 45323 | B3: 7656.62 | C3: 2
A4: 45352 | B4: 12624.82 | C4: 3 | G4: =B14/B13 -> 1.0623974
A5: 45383 | B5: 21876.66 | C5: 4 | G5: =B15/B14 -> 0.9225243
A6: 45413 | B6: 28051.92 | C6: 5 | G6: =B16/B15 -> 1.0608381
A7: 45444 | B7: 39961.96 | C7: 6
A8: 45474 | B8: 43670.51 | C8: 7
A9: 45505 | B9: 65148.8 | C9: 8
A10: 45536 | B10: 71688.68 | C10: 9
A11: 45566 | B11: 64763.79 | C11: 10
A12: 45597 | B12: 72816.87 | C12: 11
A13: 45627 | B13: 84588.28 | C13: 12
A14: 45658 | B14: 89866.37 | C14: 13
A15: 45689 | B15: 82903.91 | C15: 14
A16: 45717 | B16: 87947.63 | C16: 15
A17: 45748 | B17: 101029.5 | C17: 16
A18: 45778 | B18: 87117.84 | C18: 17
... A25: 45992 | B25: 72221.33 | C25: 24
A26: 46023 | C26: 25 | D26: =_xlfn.FORECAST.LINEAR(C26,$B$2:$B$25,$C$2:$C$25) -> 120983.3 | E26: =B25*(B14/B13) -> 76727.754
A27: 46054 | C27: 26 | D27: =_xlfn.FORECAST.LINEAR(C27,$B$2:$B$25,$C$2:$C$25) -> 125197.44 | E27: =E26*(B15/B14) -> 70783.218
A28: 46082 | C28: 27 | D28: =_xlfn.FORECAST.LINEAR(C28,$B$2:$B$25,$C$2:$C$25) -> 129411.58 | E28: =E27*(B16/B15) -> 75089.537

Sheet Raw Data
A1: TransactionID | B1: Date | C1: Region | D1: Store | E1: Category | F1: Product | G1: CustomerSegment | H1: UnitsSold | I1: UnitPrice | J1: DiscountPct | K1: UnitCost | L1: Returned
A2: TXN-105042 | B2: 04/03/2025 | C2: South | D2: S-001 | E2: Beauty | F2: Perfume 50ml | G2: Member | H2: 4 | I2: 35.34 | J2: 0.218 | K2: 10.9 | L2: No
A3: TXN-100765 | B3: 2025-04-27 | C3: South | D3: S-015 | E3: Home Goods | F3: LED Desk Lamp | G3: Member | H3: 1 | I3: 88.34 | J3: 0.171 | K3: 30.94 | L3: No
A4: TXN-103948 | B4: 03-07-2025 | C4: East | D4: E-004 | E4: Beauty | F4: Sunscreen SPF50 | G4: Member | H4: 5 | I4: 35.93 | J4: 0.1 | K4: 14.32 | L4: No
A5: TXN-100293 | B5: 04/06/2024 | C5: South | D5: S-003 | E5: Apparel | F5: Casual Dress | G5: Non-Member | H5: 2 | I5: 61.39 | J5: 0.268 | K5: 30.82 | L5: Y
A6: TXN-102532 | B6: 2025-08-31 | C6: East | D6: E-005 | E6: Electronics | F6: Bluetooth Speaker | G6: Member | H6: 1 | I6: 252.11 | J6: 0.1 | K6: 171.82 | L6: No
A7: TXN-101861 | B7: 2024-12-16 | C7: South | D7: S-008 | E7: Apparel | F7: Men's T-Shirt | G7: Member | H7: 5 | I7: 60.98 | J7: 0.365 | K7: 29.8 | L7: No
A8: TXN-101806 | B8: 15-03-2025 | C8: NORTH | D8: N-008 | E8: Home Goods | F8: Storage Bin | G8: Member | H8: 4 | I8: 25.7 | J8: 0.142 | K8: 9.84 | L8: No
A9: TXN-101433 | B9: 11/12/2025 | C9: East | D9: E-014 | E9: Apparel | F9: Men's T-Shirt | G9: Member | H9: 1 | I9: 60.08 | J9: 0.058 | L9: N
A10: TXN-102387 | B10: 2024-12-05 | C10: South | D10: S-010 | E10: Electronics | F10: Bluetooth Speaker | G10: Non-Member | H10: 7 | I10: 196.62 | J10: 0.22 | K10: 129.54 | L10: No
A11: TXN-106221 | B11: 06/06/2025 | C11: East | D11: E-004 | E11: Grocery | F11: Granola Pack | G11: Member | H11: 1 | I11: 5.96 | J11: 0.171 | K11: 3.38 | L11: No
A12: TXN-102190 | B12: 10/23/2025 | C12: East | D12: E-006 | E12: Electronics | F12: Power Bank | G12: Member | H12: 1 | I12: 138.17 | J12: 0.035 | K12: 101.8 | L12: N
A13: TXN-102531 | B13: 2025-03-20 | C13: North | D13: N-014 | E13: Apparel | F13: Women's Jeans | G13: Non-Member | H13: 1 | I13: 44.28 | J13: 0.083 | K13: 19.4 | L13: No
A14: TXN-103154 | B14: 2024-06-11 | C14: West | D14: W-014 | E14: Grocery | F14: Olive Oil 500ml | G14: Member | H14: 5 | I14: 22.33 | J14: 0.077 | K14: 13.14 | L14: No
A15: TXN-100097 | B15: 2024-07-21 | C15: East | D15: E-002 | E15: Beauty | F15: Lipstick | G15: Member | H15: 7 | I15: 19.83 | J15: 0.116 | K15: 6.48 | L15: Yes
A16: TXN-104210 | B16: 11/16/2025 | C16: West | D16: W-010 | E16: Electronics | F16: Power Bank | G16: Member | H16: 3 | I16: 276.09 | J16: 0.181 | K16: 204.7 | L16: No
A17: TXN-104693 | B17: 2025-06-22 | C17: South | D17: S-005 | E17: Beauty | F17: Lipstick | G17: Non-Member | H17: 1 | I17: 52.9 | J17: 0.074 | K17: 21.01 | L17: No
A18: TXN-104346 | B18: 06/21/2025 | C18: South | D18: S-008 | E18: Apparel | F18: Winter Jacket | G18: Member | H18: 1 | I18: 24.76 | J18: 0.194 | K18: 13.24 | L18: No
A19: TXN-102258 | B19: 2024-04-23 | C19: South | D19: S-005 | E19: Apparel | F19: Men's T-Shirt | G19: Member | H19: 3 | I19: 85.21 | J19: 0.191 | K19: 40.09 | L19: No
A20: TXN-106478 | B20: 07/10/2025 | C20: West | D20: W-012 | E20: Home Goods | F20: Ceramic Mug Set | G20: Member | H20: 1 | I20: 64.44 | J20: 0.033 | K20: 28.09 | L20: No
A21: TXN-105924 | B21: 10/08/2025 | C21: North | D21: N-006 | E21: Apparel | F21: Running Shoes | G21: Member | H21: 3 | I21: 70.67 | J21: 0.086 | K21: 33.36 | L21: No
... A34: TXN-104758 | B34: 2025-01-05 | C34: North | D34: N-007 | E34: Apparel | F34: Women's Jeans | G34: Member | H34: 1 | I34: 110.68 | J34: 0.047 | K34: 60.64 | L34: No
A35: TXN-105711 | B35: 2024-06-27 | C35: west | D35: W-011 | E35: Electronics | F35: Smart Watch | G35: Non-Member | H35: 5 | J35: 0.15 | K35: 35.01 | L35: No
A36: TXN-101679 | B36: 2025-05-30 | C36: North | D36: N-011 | E36: Electronics | F36: Wireless Earbuds | G36: Member | H36: 2 | I36: 107.85 | J36: 0.13 | K36: 71.4 | L36: No
A37: TXN-100251 | C37: East | D37: E-014 | E37: Grocery | F37: Olive Oil 500ml | G37: Member | H37: 1 | I37: 24.46 | J37: 0.065 | K37: 13.93 | L37: No
A38: TXN-104324 | B38: 13-10-2024 | C38: East | D38: E-001 | E38: Home Goods | F38: Storage Bin | G38: Member | H38: 2 | I38: 31.81 | J38: 0.057 | K38: 12.65 | L38: No
A39: TXN-101647 | B39: 2024-11-09 | C39: North | D39: N-009 | E39: Beauty | F39: Lipstick | G39: Non-Member | H39: 1 | I39: 53.04 | J39: 0.051 | K39: 22.72 | L39: N
A40: TXN-100095 | B40: 03/24/2025 | C40: EAST | D40: E-006 | E40: Grocery | F40: Olive Oil 500ml | G40: Non-Member | H40: 2 | I40: 9.75 | J40: 0.067 | K40: 5.7 | L40: No
A41: TXN-103312 | B41: 2025-02-18 | C41: East | D41: E-014 | E41: Beauty | F41: Face Moisturizer | G41: Member | H41: 3 | I41: 21.4 | J41: 0.055 | K41: 9.35 | L41: No
A42: TXN-101976 | B42: 08/22/2024 | C42: East | D42: E-012 | E42: Electronics | F42: Bluetooth Speaker | G42: Member | H42: 5 | I42: 155.28 | J42: 0.132 | K42: 106.13 | L42: No
A43: TXN-104508 | B43: 2024-09-19 | C43: North | D43: N-008 | E43: Electronics | F43: Wireless Earbuds | G43: Member | H43: 4 | I43: 159.04 | J43: 0.203 | K43: 121.91 | L43: No
A44: TXN-101580 | B44: 2025-07-04 | C44: West | D44: W-012 | E44: Home Goods | F44: LED Desk Lamp | G44: Non-Member | H44: 7 | I44: 19.52 | J44: 0.153 | K44: 9.46 | L44: No
A45: TXN-102446 | B45: 2025-05-13 | C45: South | D45: S-010 | E45: Apparel | F45: Running Shoes | G45: Non-Member | H45: 1 | I45: 111.81 | J45: 0.328 | K45: 58.78 | L45: No
A46: TXN-101061 | B46: 2025-02-24 | C46: South | D46: S-012 | E46: Apparel | F46: Women's Jeans | G46: Non-Member | H46: 6 | I46: 108.2 | K46: 53.41 | L46: No
A47: TXN-102571 | B47: 2025-12-10 | C47: South | D47: S-003 | E47: Beauty | F47: Lipstick | G47: Non-Member | H47: 1 | I47: 8 | J47: 0.177 | K47: 3.09 | L47: No
A48: TXN-103730 | B48: 05/29/2025 | C48: North | D48: N-015 | E48: Grocery | F48: Granola Pack | G48: Non-Member | H48: 1 | I48: 14.51 | J48: 0.084 | K48: 9.56 | L48: No
A49: TXN-100768 | B49: 06-10-2025 | C49: East | D49: E-013 | E49: Electronics | F49: Smart Watch | G49: Non-Member | H49: 1 | I49: 118.87 | J49: 0.055 | K49: 90.18 | L49: No
A50: TXN-100948 | B50: 06/30/2025 | C50: East | D50: E-009 | E50: Apparel | F50: Casual Dress | G50: Member | H50: 1 | I50: 72.4 | J50: 0.081 | K50: 39.31 | L50: No
A51: TXN-104691 | B51: 2024-11-19 | C51: East | D51: E-010 | E51: Apparel | F51: Winter Jacket | H51: 5 | I51: 69.42 | J51: 0.12 | K51: 34.6 | L51: No
A52: TXN-101903 | B52: 2025-06-05 | C52: South | D52: S-008 | E52: Home Goods | F52: Throw Pillow | G52: Non-Member | H52: 1 | I52: 63.03 | J52: 0.333 | K52: 26.82 | L52: No
A53: TXN-102761 | B53: 2025-04-26 | C53: East | D53: E-002 | E53: Home Goods | F53: Ceramic Mug Set | G53: Non-Member | H53: 1 | I53: 89.48 | J53: 0.108 | K53: 35.37 | L53: No
A54: TXN-104775 | B54: 05-07-2025 | C54: North | D54: N-013 | E54: Grocery | F54: Granola Pack | G54: Non-Member | H54: 2 | I54: 12.51 | J54: 0.067 | K54: 7.35 | L54: No
A55: TXN-106026 | C55: EAST | D55: E-014 | E55: Electronics | F55: Smart Watch | G55: Member | H55: 9 | I55: 142.57 | J55: 0.071 | K55: 107.17 | L55: No
A56: TXN-102518 | B56: 2025-10-08 | C56: East | D56: E-014 | E56: Home Goods | F56: LED Desk Lamp | G56: Member | H56: 2 | I56: 88.67 | J56: 0.095 | K56: 43.64 | L56: No
A57: TXN-101533 | B57: 08/19/2025 | C57: North | D57: N-009 | E57: Home Goods | F57: Bath Towel Set | G57: Member | H57: 4 | I57: 71.25 | J57: 0.051 | K57: 32.37 | L57: No
A58: TXN-105699 | B58: 2024-09-27 | C58: North | D58: N-001 | E58: Grocery | F58: Organic Coffee 12oz | G58: Non-Member | H58: 3 | I58: 11.14 | J58: 0.122 | K58: 7.45 | L58: No
A59: TXN-104565 | B59: 2025-09-27 | C59: West | D59: W-003 | E59: Grocery | F59: Organic Coffee 12oz | G59: Non-Member | H59: 10 | I59: 6.3 | J59: 0.165 | K59: 3.51 | L59: No
A60: TXN-100996 | B60: 2024-04-28 | C60: South | D60: S-004 | E60: Beauty | F60: Lipstick | G60: Member | H60: 1 | I60: 22.97 | J60: 0.187 | K60: 8.59 | L60: N
A61: TXN-102881 | B61: 2024-10-07 | C61: East | E61: Grocery | F61: Snack Box | G61: Member | H61: 4 | I61: 9.44 | J61: 0.068 | K61: 6.42 | L61: No
A62: TXN-100329 | B62: 07/07/2025 | C62: North | D62: N-007 | E62: Apparel | F62: Casual Dress | G62: Non-Member | H62: 3 | I62: 64.98 | K62: 32.2 | L62: No
A63: TXN-100317 | B63: 06/06/2025 | C63: West | D63: W-008 | E63: Electronics | F63: Laptop Stand | G63: Member | H63: 3 | I63: 234.45 | J63: 0.026 | K63: 163.65 | L63: No
A64: TXN-104361 | B64: 2025-12-17 | C64: East | E64: Home Goods | F64: Ceramic Mug Set | G64: Member | H64: 3 | I64: 51.36 | J64: 0.129 | K64: 24.79 | L64: Yes
A65: TXN-104709 | B65: 2024-11-05 | C65: West | D65: W-004 | E65: Home Goods | F65: Ceramic Mug Set | G65: Member | H65: 6 | I65: 11.74 | J65: 0.069 | K65: 4.26 | L65: Yes
A66: TXN-102185 | B66: 2024-12-17 | C66: East | D66: E-007 | E66: Home Goods | F66: LED Desk Lamp | G66: Member | H66: 1 | I66: 85.17 | J66: 0.06 | K66: 41.24 | L66: No
A67: TXN-105081 | B67: 2024-08-14 | C67: East | D67: E-007 | E67: Home Goods | F67: Bath Towel Set | G67: Non-Member | H67: 500 | I67: 15.69 | J67: 0.113 | K67: 7.45 | L67: No
A68: TXN-100655 | B68: 16-12-2024 | C68: West | D68: W-013 | E68: Beauty | F68: Lipstick | G68: Member | H68: 1 | I68: 35.09 | J68: 0.082 | K68: 12.9 | L68: No
A69: TXN-100722 | B69: 2025-04-21 | C69: West | D69: W-011 | E69: Beauty | F69: Face Moisturizer | G69: Non-Member | H69: 2 | J69: 0.169 | L69: No
A70: TXN-100318 | B70: 2024-07-06 | C70: EAST | D70: E-007 | E70: Electronics | F70: Wireless Earbuds | G70: Non-Member | H70: 1 | I70: 228.84 | J70: 0 | K70: 149.3 | L70: No
A71: TXN-104109 | B71: 2025-11-20 | C71: South | D71: S-009 | E71: Home Goods | F71: Ceramic Mug Set | G71: Non-Member | H71: 6 | I71: 42.77 | J71: 0.105 | K71: 15.08 | L71: Yes
A72: TXN-104842 | B72: 11/26/2025 | C72: South | D72: S-007 | E72: Beauty | F72: Perfume 50ml | G72: Member | H72: 1 | I72: 38.66 | J72: 0.266 | K72: 16.49 | L72: N
A73: TXN-104706 | B73: 2025-12-08 | C73: South | D73: S-013 | E73: Electronics | F73: Power Bank | G73: Member | H73: 3 | I73: 249.32 | J73: 0.338 | K73: 164.05 | L73: No
A74: TXN-102717 | B74: 2025-07-04 | C74: West | D74: W-005 | E74: Electronics | F74: Bluetooth Speaker | G74: Non-Member | H74: 1 | I74: 183.46 | J74: 0.151 | K74: 129.6 | L74: No
A75: TXN-100943 | B75: 2025-12-11 | C75: EAST | D75: E-013 | E75: Grocery | F75: Granola Pack | G75: Non-Member | H75: 1 | I75: 17.67 | J75: 0.006 | K75: 12.24 | L75: No
A76: TXN-102455 | B76: 11-11-2025 | C76: West | D76: W-010 | E76: Home Goods | F76: LED Desk Lamp | G76: Member | H76: 1 | I76: 82.65 | J76: 0.133 | K76: 40.77 | L76: No
A77: TXN-102557 | B77: 02/24/2025 | C77: South | D77: S-007 | E77: Apparel | F77: Women's Jeans | G77: Member | H77: 3 | I77: 45.89 | J77: 0.394 | K77: 19.33 | L77: No
A78: TXN-103464 | B78: 2025-03-08 | C78: East | D78: E-009 | E78: Beauty | F78: Face Moisturizer | G78: Non-Member | H78: 1 | J78: 0.168 | K78: 18.88 | L78: No
A79: TXN-102659 | B79: 11/24/2025 | C79: North | D79: N-005 | E79: Beauty | F79: Lipstick | G79: Non-Member | H79: 1 | I79: 29.37 | J79: 0.087 | K79: 9.42 | L79: No
A80: TXN-101669 | B80: 07-12-2024 | C80: South | D80: S-005 | E80: Electronics | F80: Smart Watch | G80: Member | H80: 1 | I80: 56.71 | J80: 0.297 | K80: 42.46 | L80: No
A81: TXN-101342 | B81: 2025-04-05 | C81: East | D81: E-011 | E81: Home Goods | F81: Throw Pillow | G81: Member | H81: 1 | I81: 75.99 | J81: 0 | K81: 27.77 | L81: No
A82: TXN-105436 | B82: 08-09-2025 | C82: North | D82: N-009 | E82: Beauty | F82: Lipstick | G82: Member | H82: 5 | I82: 48.71 | J82: 0.182 | K82: 19.49 | L82: No
A83: TXN-103607 | B83: February 27, 2025 | C83: East | D83: E-002 | E83: Grocery | F83: Organic Coffee 12oz | G83: Member | H83: 7 | I83: 6.62 | J83: 0.049 | K83: 3.77 | L83: No
A84: TXN-104832 | B84: 09/27/2024 | C84: East | D84: E-001 | E84: Apparel | F84: Men's T-Shirt | G84: Non-Member | H84: 1 | I84: 66.83 | J84: 0.114 | K84: 34.15 | L84: No
A85: TXN-101985 | B85: 06/13/2025 | C85: West | D85: W-003 | E85: Apparel | F85: Men's T-Shirt | G85: Non-Member | H85: 4 | I85: 82.58 | J85: 0.008 | K85: 37.05 | L85: No
A86: TXN-102260 | B86: 2024-10-10 | C86: North | D86: N-013 | E86: Apparel | F86: Men's T-Shirt | G86: Member | H86: 6 | I86: 53.68 | J86: 0.009 | K86: 25.95 | L86: No
A87: TXN-104896 | B87: 2024-07-20 | C87: East | D87: E-003 | E87: Home Goods | F87: Storage Bin | G87: Member | H87: 6 | I87: 31.63 | J87: 0.138 | K87: 11.61 | L87: No
A88: TXN-101705 | B88: 2025-09-24 | C88: East | D88: E-012 | E88: Grocery | F88: Snack Box | G88: Non-Member | H88: 1 | I88: 9.09 | J88: 0 | K88: 5.92 | L88: N
A89: TXN-103709 | B89: 09/13/2025 | C89: South | D89: S-002 | E89: Electronics | F89: Wireless Earbuds | G89: Member | H89: 1 | I89: 154.63 | J89: 0.117 | K89: 118.3 | L89: No
A90: TXN-104826 | B90: 2025-01-20 | C90: South | D90: S-001 | E90: Apparel | F90: Winter Jacket | G90: Non-Member | H90: 11 | I90: 88.49 | J90: 0.198 | K90: 37.96 | L90: No
... A102: TXN-105366 | B102: 2025-03-25 | C102: North | D102: N-012 | E102: Home Goods | F102: Storage Bin | G102: Member | H102: 4 | I102: 13.33 | J102: 0.002 | K102: 6.54 | L102: No
A103: TXN-106079 | B103: 10/30/2025 | C103: West | D103: W-011 | E103: Beauty | F103: Shampoo 300ml | G103: Member | H103: 1 | J103: 0.085 | K103: 4.55 | L103: N
A104: TXN-103288 | B104: 2025-10-17 | C104: North | D104: N-010 | E104: Electronics | F104: Bluetooth Speaker | G104: Member | H104: 2 | I104: 190.95 | J104: 0.027 | K104: 136.5 | L104: No
A105: TXN-101344 | B105: 11/09/2024 | C105: South | D105: S-015 | E105: Beauty | F105: Sunscreen SPF50 | G105: Member | H105: 2 | I105: 45.17 | K105: 19.66 | L105: No
A106: TXN-105127 | B106: 2025-12-10 | C106: East | D106: E-009 | E106: Electronics | F106: Smart Watch | G106: Non-Member | H106: 4 | I106: 155.12 | J106: 0.07 | K106: 105.84 | L106: No
A107: TXN-100836 | B107: 2025-03-12 | C107: East | D107: E-003 | E107: Grocery | F107: Olive Oil 500ml | G107: Member | H107: 6 | I107: 20.1 | J107: 0.097 | K107: 12.21 | L107: No
A108: TXN-102906 | B108: 06/16/2024 | C108: NORTH | D108: N-015 | E108: Apparel | F108: Casual Dress | G108: Member | H108: 2 | I108: 67.1 | J108: 0 | K108: 30.66 | L108: No
A109: TXN-102082 | B109: 2025-01-06 | C109: West | D109: W-007 | E109: Grocery | F109: Sparkling Water 12pk | G109: Member | H109: 2 | I109: 10.53 | J109: 0.01 | K109: 5.82 | L109: No
A110: TXN-100354 | B110: 28-02-2024 | C110: West | D110: W-009 | E110: Electronics | F110: Smart Watch | G110: Non-Member | H110: 4 | I110: 217.95 | J110: 0.011 | K110: 168.22 | L110: No
A111: TXN-105725 | B111: 2025-04-11 | C111: East | D111: E-002 | E111: Grocery | F111: Sparkling Water 12pk | G111: Member | H111: 2 | J111: 0.083 | K111: 11.66 | L111: No
A112: TXN-102176 | B112: 05/02/2025 | C112: North | D112: N-014 | E112: Electronics | F112: Smart Watch | G112: Non-Member | H112: 2 | I112: 207.83 | J112: 0.107 | K112: 166.21 | L112: No
A113: TXN-102196 | B113: 2025-10-07 | C113: North | D113: N-014 | E113: Apparel | F113: Running Shoes | G113: Member | H113: 4 | I113: 54.77 | J113: 0.138 | K113: 26.17 | L113: No
A114: TXN-103793 | B114: 2025-01-12 | C114: East | D114: E-002 | E114: Grocery | F114: Sparkling Water 12pk | H114: 1 | I114: 4.23 | J114: 0.157 | K114: 2.9 | L114: No
A115: TXN-102850 | B115: 2024-12-23 | C115: East | D115: E-015 | E115: Electronics | F115: Bluetooth Speaker | G115: Non-Member | H115: 1 | I115: 211.91 | J115: 0.086 | K115: 160.63 | L115: No
A116: TXN-102344 | B116: 2025-06-29 | C116: NORTH | E116: Electronics | F116: Smart Watch | G116: Member | H116: 200 | I116: 149.26 | J116: 0.15 | K116: 109.24 | L116: No
A117: TXN-104853 | B117: 01/14/2025 | C117: West | D117: W-011 | E117: Home Goods | F117: LED Desk Lamp | G117: Non-Member | H117: 7 | I117: 53.31 | J117: 0.053 | K117: 23.06 | L117: No
A118: TXN-106407 | B118: 2024-05-07 | C118: East | D118: E-005 | E118: Beauty | F118: Sunscreen SPF50 | G118: Member | H118: 1 | I118: 28.47 | J118: 0 | K118: 10.16 | L118: No
A119: TXN-100517 | B119: 2025-01-17 | C119: West | D119: W-011 | E119: Electronics | F119: Power Bank | H119: 4 | I119: 99.24 | J119: 0.096 | K119: 73.52 | L119: No
A120: TXN-106363 | B120: 2025-01-02 | C120: West | E120: Apparel | F120: Men's T-Shirt | G120: Non-Member | H120: 2 | I120: 72.41 | J120: 0.053 | K120: 37.45 | L120: No
A121: TXN-100908 | B121: 12/09/2024 | C121: East | D121: E-005 | E121: Beauty | F121: Perfume 50ml | G121: Non-Member | H121: 3 | I121: 45.85 | J121: 0.144 | K121: 16.81 | L121: No
A122: TXN-105222 | B122: 2025-11-10 | C122: South | D122: S-006 | E122: Grocery | F122: Granola Pack | G122: Non-Member | H122: -1 | I122: 13.09 | J122: 0.307 | K122: 7.54 | L122: No
A123: TXN-100319 | B123: 2025-03-27 | C123: West | D123: W-005 | E123: Electronics | F123: Smart Watch | G123: Member | H123: 4 | I123: 88.26 | J123: 0.05 | K123: 64.91 | L123: No
...
